Metadata-Version: 2.1
Name: qcfoptions
Version: 0.2.0
Summary: Option Calculator and Simulator
Home-page: https://github.com/austingriffith94/qcfoptions
Author: Austin Griffith
Author-email: austgriffia@gmail.com
License: MIT
Platform: UNKNOWN
Classifier: Development Status :: 3 - Alpha
Classifier: Intended Audience :: Financial and Insurance Industry
Classifier: License :: OSI Approved :: MIT License
Classifier: Natural Language :: English
Classifier: Programming Language :: Python :: 3
Requires-Python: ~=3.0
